robocorp/log/__init__.py
robocorp/log/_ast_utils.py
robocorp/log/_auto_logging_setup.py
robocorp/log/_collect_stats.py
robocorp/log/_config.py
robocorp/log/_constants.py
robocorp/log/_convert_units.py
robocorp/log/_decoder.py
robocorp/log/_decoder_spec.py
robocorp/log/_index_v3.py
robocorp/log/_lifecycle_hooks.py
robocorp/log/_log_formatting.py
robocorp/log/_log_redacter.py
robocorp/log/_logger_instances.py
robocorp/log/_null.py
robocorp/log/_obj_info_repr.py
robocorp/log/_on_exit_context_manager.py
robocorp/log/_rewrite_ast_add_callbacks.py
robocorp/log/_rewrite_filtering.py
robocorp/log/_rewrite_importhook.py
robocorp/log/_robo_logger.py
robocorp/log/_robo_output_impl.py
robocorp/log/_safe_write_to_stream.py
robocorp/log/_sensitive_variable_names.py
robocorp/log/_suppress_helper.py
robocorp/log/console.py
robocorp/log/protocols.py
robocorp/log/py.typed
robocorp/log/pyproject_config.py
robocorp/log/redirect.py
robocorp_log-3.0.0.dist-info/LICENSE
robocorp_log-3.0.0.dist-info/METADATA
robocorp_log-3.0.0.dist-info/WHEEL
robocorp_log-3.0.0.dist-info/RECORD
