Metadata-Version: 2.1
Name: robocorp-log
Version: 3.0.0
Summary: Automatic trace logging for Python
Home-page: https://github.com/robocorp/robocorp/
License: Apache-2.0
Author: Fabio Z.
Author-email: fabio@robocorp.com
Requires-Python: >=3.9.2,<4.0.0
Classifier: Development Status :: 4 - Beta
Classifier: License :: OSI Approved :: Apache Software License
Classifier: Programming Language :: Python :: 3
Classifier: Programming Language :: Python :: 3.10
Classifier: Programming Language :: Python :: 3.11
Classifier: Programming Language :: Python :: 3.12
Classifier: Programming Language :: Python :: 3.9
Classifier: Topic :: Software Development :: Libraries :: Python Modules
Classifier: Topic :: System :: Logging
Requires-Dist: psutil (>=5.9,<6.0)
Requires-Dist: tomli (>=2.0.1,<3.0.0) ; python_version < "3.11"
Project-URL: Repository, https://github.com/robocorp/robocorp/
